marsa/__init__.py
marsa/__main__.py
marsa/config.py
marsa/export.py
marsa/matching.py
marsa/pipeline.py
marsa/sentiment.py
marsa/utils.py
marsapy-0.1.0.dist-info/METADATA
marsapy-0.1.0.dist-info/WHEEL
marsapy-0.1.0.dist-info/entry_points.txt
marsapy-0.1.0.dist-info/licenses/LICENSE
marsapy-0.1.0.dist-info/RECORD
