Metadata-Version: 2.4
Name: marsapy
Version: 0.1.0
Summary: MARSA (Multiple-Aspect Rule-Based Sentiment Annotator) is a lightweight assistant for aspect-sentiment pair extraction and correction.
Project-URL: Homepage, https://github.com/anj0la/marsa
Project-URL: Bug Tracker, https://github.com/anj0la/marsa/issues
Author-email: Anjola Aina <anjola.aina@gmail.com>
License-Expression: MIT
License-File: LICENSE
Classifier: Development Status :: 3 - Alpha
Classifier: Intended Audience :: Developers
Classifier: Intended Audience :: Science/Research
Classifier: License :: OSI Approved :: MIT License
Classifier: Operating System :: OS Independent
Classifier: Programming Language :: Python :: 3 :: Only
Classifier: Programming Language :: Python :: 3.8
Classifier: Programming Language :: Python :: 3.9
Classifier: Programming Language :: Python :: 3.10
Classifier: Programming Language :: Python :: 3.11
Classifier: Programming Language :: Python :: 3.12
Classifier: Topic :: Scientific/Engineering :: Artificial Intelligence
Classifier: Topic :: Text Processing :: Linguistic
Requires-Python: <3.13,>=3.8
Requires-Dist: emoji>=1.2
Requires-Dist: numpy>=1.19
Requires-Dist: pandas>=1.1
Requires-Dist: pip>=25.0.1
Requires-Dist: pyyaml>=5.4
Requires-Dist: scikit-learn>=0.24
Requires-Dist: spacy>=3.0
Requires-Dist: torch>=2.5.1
Requires-Dist: torchaudio>=2.5.1
Requires-Dist: torchvision>=0.20.1
Requires-Dist: transformers>=4.46.3
Requires-Dist: vadersentiment>=3.3.2
